quokka_web/__init__.py
quokka_web/agent.py
quokka_web/base_class/__init__.py
quokka_web/base_class/crawler.py
quokka_web/base_class/exception.py
quokka_web/base_class/page_handler.py
quokka_web/base_class/page_parser.py
quokka_web/browser_mgr/__init__.py
quokka_web/browser_mgr/exception.py
quokka_web/browser_mgr/main.py
quokka_web/data_extractor/__init__.py
quokka_web/data_extractor/main.py
quokka_web/data_extractor/utils.py
quokka_web/page_interactor/__init__.py
quokka_web/page_interactor/main.py
quokka_web/page_interactor/modules/__init__.py
quokka_web/page_interactor/modules/click_handler.py
quokka_web/page_interactor/modules/common_handler.py
quokka_web/page_interactor/modules/handler.py
quokka_web/page_interactor/modules/scroll_handler.py
quokka_web-0.0.2.0.dist-info/LICENCE
quokka_web-0.0.2.0.dist-info/METADATA
quokka_web-0.0.2.0.dist-info/WHEEL
quokka_web-0.0.2.0.dist-info/top_level.txt
quokka_web-0.0.2.0.dist-info/RECORD
