Metadata-Version: 2.1
Name: quokka-web
Version: 0.0.2.0
Summary: Quokka is a powerful Python library built on top of Playwright, designed to simplify browser automation and web scraping tasks. With Quokka, you can easily navigate web pages, extract data, and interact with page elements using an intuitive API. Quokka supports asynchronous and parallel execution, making it suitable for a wide range of IO and CPU-bound workloads. Get started with Quokka to streamline your browser automation and web scraping workflows.
Author: steveflyer
Author-email: steveflyer7@gmail.com
License-File: LICENCE
Requires-Dist: lxml
Requires-Dist: gembox
Requires-Dist: pathlib
Requires-Dist: aiofiles
Requires-Dist: playwright
Requires-Dist: beautifulsoup4
Requires-Dist: fake-useragent
